statstream/__init__.py
statstream/approximate.py
statstream/exact.py
statstream-22.1.0.dist-info/LICENSE
statstream-22.1.0.dist-info/METADATA
statstream-22.1.0.dist-info/WHEEL
statstream-22.1.0.dist-info/top_level.txt
statstream-22.1.0.dist-info/RECORD
